[
  {
    "name": "White House",
    "streetAddress": "1600 Pennsylvania Ave",
    "city": "Washington",
    "state": "D.C.",
    "zipCode": "20500",
    "phoneNumber": "2024561111",
    "beerLicenseNumber": "979733216",
    "paymentMethod": "Cash",
    "loadingDockInfo": "Full bay area with dock levelers. Can accept full-size trucks with pallets of goods.",
    "deliveryConstraints": "8:00 AM to 4:15 PM",
    "pointOfContact": "Bill Clinton"
  },
  {
    "name": "Beverage Hut",
    "streetAddress": "437 Cherokee Blvd",
    "city": "Spokane",
    "state": "WA",
    "zipCode": "99201",
    "phoneNumber": "5094218866",
    "beerLicenseNumber": "090434108",
    "paymentMethod": "EBT",
    "loadingDockInfo": "Regular door. Hand truck only.",
    "deliveryConstraints": "2:30 PM to 9:00 PM",
    "pointOfContact": "James Madison"
  },
  {
    "name": "The Corner Street Corner Store",
    "streetAddress": "66445 Corner Street",
    "city": "Atlanta",
    "state": "Texas",
    "zipCode": "75551",
    "phoneNumber": "4308871232",
    "beerLicenseNumber": "672821239",
    "paymentMethod": "Fintech",
    "loadingDockInfo": "Freight elevator.  No pallets but wide doors.",
    "deliveryConstraints": "5:45 AM to 7:45 AM",
    "pointOfContact": "Rutherford Hayes"
  }
]